setup.py
ly_cdn_tools/__init__.py
ly_cdn_tools.egg-info/PKG-INFO
ly_cdn_tools.egg-info/SOURCES.txt
ly_cdn_tools.egg-info/dependency_links.txt
ly_cdn_tools.egg-info/requires.txt
ly_cdn_tools.egg-info/top_level.txt
ly_cdn_tools/warmup/__init__.py
ly_cdn_tools/warmup/aliyun.py
ly_cdn_tools/warmup/core/__init__.py
ly_cdn_tools/warmup/core/manager.py