Metadata-Version: 1.1
Name: ly-cdn-tools
Version: 0.2
Summary: longyuan cdn tools
Home-page: UNKNOWN
Author: wangying
Author-email: wangying@dragonest.com
License: LGPL
Platform: UNKNOWN
Classifier: Programming Language :: Python :: 2.7
Classifier: Topic :: Software Development :: Libraries :: Python Modules
